othello/__init__.py
othello/othello.py
othello/othello.so
othelloc/__init__.py
othelloc/othello.py
othelloc/othello.so
othelloc-0.2.3.dist-info/METADATA
othelloc-0.2.3.dist-info/WHEEL
othelloc-0.2.3.dist-info/top_level.txt
othelloc-0.2.3.dist-info/RECORD
