Metadata-Version: 2.1
Name: othelloc
Version: 0.2.3
Summary: C library for Othello game
Author: Hunter Livesay
License: MIT
